odoo/addons/budget_control_account_asset_management/README.rst
odoo/addons/budget_control_account_asset_management/__init__.py
odoo/addons/budget_control_account_asset_management/__manifest__.py
odoo/addons/budget_control_account_asset_management/models/__init__.py
odoo/addons/budget_control_account_asset_management/models/account_asset.py
odoo/addons/budget_control_account_asset_management/models/account_asset_line.py
odoo/addons/budget_control_account_asset_management/models/res_company.py
odoo/addons/budget_control_account_asset_management/models/res_config_settings.py
odoo/addons/budget_control_account_asset_management/readme/CONTRIBUTORS.md
odoo/addons/budget_control_account_asset_management/readme/DESCRIPTION.md
odoo/addons/budget_control_account_asset_management/readme/USAGE.md
odoo/addons/budget_control_account_asset_management/static/description/icon.png
odoo/addons/budget_control_account_asset_management/static/description/index.html
odoo/addons/budget_control_account_asset_management/tests/__init__.py
odoo/addons/budget_control_account_asset_management/tests/test_budget_control_asset.py
odoo/addons/budget_control_account_asset_management/views/account_asset.xml
odoo/addons/budget_control_account_asset_management/views/res_config_settings_views.xml
odoo_addon_budget_control_account_asset_management-18.0.1.0.0.1.dist-info/METADATA
odoo_addon_budget_control_account_asset_management-18.0.1.0.0.1.dist-info/WHEEL
odoo_addon_budget_control_account_asset_management-18.0.1.0.0.1.dist-info/top_level.txt
odoo_addon_budget_control_account_asset_management-18.0.1.0.0.1.dist-info/RECORD
